tradernetwork.py
src/__init__.py
src/base.py
src/proxy.py
src/client/__init__.py
src/client/cluster.py
src/client/memory.py
src/cluster/__init__.py
src/cluster/cluster.py
src/cluster/memory_controller.py
src/cluster/node_controller.py
src/cluster/node_tracker.py
src/memory/__init__.py
src/memory/handler.py
src/memory/index.py
src/memory/memory.py
src/node/__init__.py
src/node/node.py
src/service/__init__.py
src/service/service.py
src/service/service_table.py
tests/__init__.py
tradernetwork-0.0.7.dist-info/METADATA
tradernetwork-0.0.7.dist-info/WHEEL
tradernetwork-0.0.7.dist-info/top_level.txt
tradernetwork-0.0.7.dist-info/RECORD
